GenWoYiqiWanWin32Kaifa/README.md
GenWoYiqiWanWin32Kaifa/__init__.py
GenWoYiqiWanWin32Kaifa/__main__.py
GenWoYiqiWanWin32Kaifa/file.epub
GenWoYiqiWanWin32Kaifa/index.html
GenWoYiqiWanWin32Kaifa/css/__init__.py
GenWoYiqiWanWin32Kaifa/css/annotations.css
GenWoYiqiWanWin32Kaifa/css/main.css
GenWoYiqiWanWin32Kaifa/css/normalize.css
GenWoYiqiWanWin32Kaifa/css/popup.css
GenWoYiqiWanWin32Kaifa/font/__init__.py
GenWoYiqiWanWin32Kaifa/font/fontello.eot
GenWoYiqiWanWin32Kaifa/font/fontello.svg
GenWoYiqiWanWin32Kaifa/font/fontello.ttf
GenWoYiqiWanWin32Kaifa/font/fontello.woff
GenWoYiqiWanWin32Kaifa/img/__init__.py
GenWoYiqiWanWin32Kaifa/img/annotator-glyph-sprite.png
GenWoYiqiWanWin32Kaifa/img/annotator-icon-sprite.png
GenWoYiqiWanWin32Kaifa/img/apple-touch-icon.png
GenWoYiqiWanWin32Kaifa/img/cancelfullscreen.png
GenWoYiqiWanWin32Kaifa/img/close.png
GenWoYiqiWanWin32Kaifa/img/fullscreen.png
GenWoYiqiWanWin32Kaifa/img/loader.gif
GenWoYiqiWanWin32Kaifa/img/menu-icon.png
GenWoYiqiWanWin32Kaifa/img/save.png
GenWoYiqiWanWin32Kaifa/img/saved.png
GenWoYiqiWanWin32Kaifa/img/settings-s.png
GenWoYiqiWanWin32Kaifa/img/settings.png
GenWoYiqiWanWin32Kaifa/img/star.png
GenWoYiqiWanWin32Kaifa/js/__init__.py
GenWoYiqiWanWin32Kaifa/js/epub.js
GenWoYiqiWanWin32Kaifa/js/epub.min.js
GenWoYiqiWanWin32Kaifa/js/epub.min.map
GenWoYiqiWanWin32Kaifa/js/hooks.min.js
GenWoYiqiWanWin32Kaifa/js/hooks.min.map
GenWoYiqiWanWin32Kaifa/js/reader.js
GenWoYiqiWanWin32Kaifa/js/reader.js.map
GenWoYiqiWanWin32Kaifa/js/reader.min.js
GenWoYiqiWanWin32Kaifa/js/reader.min.map
GenWoYiqiWanWin32Kaifa/js/hooks/__init__.py
GenWoYiqiWanWin32Kaifa/js/hooks/extensions/__init__.py
GenWoYiqiWanWin32Kaifa/js/hooks/extensions/highlight.js
GenWoYiqiWanWin32Kaifa/js/libs/__init__.py
GenWoYiqiWanWin32Kaifa/js/libs/jquery.min.js
GenWoYiqiWanWin32Kaifa/js/libs/localforage.min.js
GenWoYiqiWanWin32Kaifa/js/libs/screenfull.js
GenWoYiqiWanWin32Kaifa/js/libs/screenfull.min.js
GenWoYiqiWanWin32Kaifa/js/libs/zip.min.js
gen_wo_yiqi_wan_win32_kaifa-2024.3.2.0.dist-info/METADATA
gen_wo_yiqi_wan_win32_kaifa-2024.3.2.0.dist-info/WHEEL
gen_wo_yiqi_wan_win32_kaifa-2024.3.2.0.dist-info/entry_points.txt
gen_wo_yiqi_wan_win32_kaifa-2024.3.2.0.dist-info/top_level.txt
gen_wo_yiqi_wan_win32_kaifa-2024.3.2.0.dist-info/RECORD
